pyramid_closure
